tests/__init__.py
tests/test_user.py
flask_cf_framework_gleisonbs-0.0.2.dist-info/LICENSE
flask_cf_framework_gleisonbs-0.0.2.dist-info/METADATA
flask_cf_framework_gleisonbs-0.0.2.dist-info/WHEEL
flask_cf_framework_gleisonbs-0.0.2.dist-info/top_level.txt
flask_cf_framework_gleisonbs-0.0.2.dist-info/RECORD
