Metadata-Version: 2.1
Name: flask-cf-framework-gleisonbs
Version: 0.0.2
Summary: A route handler for Google Cloud Functions
Home-page: https://github.com/gleisonbs/flask-cf-framework
Author: Gleison Batista
License: UNKNOWN
Platform: UNKNOWN
Classifier: Programming Language :: Python :: 3
Classifier: License :: OSI Approved :: MIT License
Classifier: Operating System :: OS Independent
Requires-Python: >=3.6
